punktdict/README.MD
punktdict/__init__.py
punktdict/requirements.txt
punktdict/thirdparty.json
punktdict-0.10.dist-info/LICENSE.rst
punktdict-0.10.dist-info/METADATA
punktdict-0.10.dist-info/WHEEL
punktdict-0.10.dist-info/top_level.txt
punktdict-0.10.dist-info/RECORD
